poetry_build_testing_12345/__init__.py
poetry_build_testing_12345-0.1.6.dist-info/WHEEL
poetry_build_testing_12345-0.1.6.dist-info/METADATA
poetry_build_testing_12345-0.1.6.dist-info/RECORD
