Metadata-Version: 2.1
Name: poetry-build-testing-12345
Version: 0.1.6
Summary: 
Author: Your Name
Author-email: you@example.com
Requires-Python: >=3.9,<4.0
Classifier: Programming Language :: Python :: 3
Classifier: Programming Language :: Python :: 3.9
Classifier: Programming Language :: Python :: 3.10
Classifier: Programming Language :: Python :: 3.11
Provides-Extra: boto3
Requires-Dist: boto3 (>=1.24.89,<2.0.0); extra == "boto3"
Requires-Dist: requests (>=2.28.1,<3.0.0)
